gradio_highlightedtextbox/__init__.py
gradio_highlightedtextbox/highlightedtextbox.py
gradio_highlightedtextbox/highlightedtextbox.pyi
gradio_highlightedtextbox/py.typed
gradio_highlightedtextbox/templates/component/index.js
gradio_highlightedtextbox/templates/component/style.css
gradio_highlightedtextbox/templates/example/index.js
gradio_highlightedtextbox/templates/example/style.css
gradio_highlightedtextbox-0.0.13.dist-info/METADATA
gradio_highlightedtextbox-0.0.13.dist-info/WHEEL
gradio_highlightedtextbox-0.0.13.dist-info/RECORD
